setup.py
myadicalcpkg/__init__.py
myadicalcpkg/calculator.py
myadicalcpkg.egg-info/PKG-INFO
myadicalcpkg.egg-info/SOURCES.txt
myadicalcpkg.egg-info/dependency_links.txt
myadicalcpkg.egg-info/top_level.txt