Metadata-Version: 2.1
Name: myadicalcpkg
Version: 0.0.1
Summary: ADI Python Package Module
Home-page: https://github.com/vasu819/mydemopackage
Author: vschennu
Author-email: vschennu@gmail.com
Classifier: Programming Language :: Python :: 3
Classifier: Operating System :: OS Independent
